{
	"configurations" : 
	[
		{
			"directories" : 
			[
				{
					"build" : ".",
					"childIndexes" : 
					[
						1,
						2
					],
					"hasInstallRule" : true,
					"jsonFile" : "directory-.-Debug-44aad55c99414475246e.json",
					"minimumCMakeVersion" : 
					{
						"string" : "3.14"
					},
					"projectIndex" : 0,
					"source" : "."
				},
				{
					"build" : "flutter",
					"jsonFile" : "directory-flutter-Debug-79e0260f2327d8493c28.json",
					"minimumCMakeVersion" : 
					{
						"string" : "3.14"
					},
					"parentIndex" : 0,
					"projectIndex" : 0,
					"source" : "flutter",
					"targetIndexes" : 
					[
						0,
						2,
						3
					]
				},
				{
					"build" : "runner",
					"jsonFile" : "directory-runner-Debug-86f38b7dcb6f33eb04e4.json",
					"minimumCMakeVersion" : 
					{
						"string" : "3.14"
					},
					"parentIndex" : 0,
					"projectIndex" : 1,
					"source" : "runner",
					"targetIndexes" : 
					[
						1
					]
				}
			],
			"name" : "Debug",
			"projects" : 
			[
				{
					"childIndexes" : 
					[
						1
					],
					"directoryIndexes" : 
					[
						0,
						1
					],
					"name" : "flutter_chat_example",
					"targetIndexes" : 
					[
						0,
						2,
						3
					]
				},
				{
					"directoryIndexes" : 
					[
						2
					],
					"name" : "runner",
					"parentIndex" : 0,
					"targetIndexes" : 
					[
						1
					]
				}
			],
			"targets" : 
			[
				{
					"directoryIndex" : 1,
					"id" : "flutter_assemble::@2bb09fbb03a373b2cb34",
					"jsonFile" : "target-flutter_assemble-Debug-7fd3b1731921c52b9299.json",
					"name" : "flutter_assemble",
					"projectIndex" : 0
				},
				{
					"directoryIndex" : 2,
					"id" : "flutter_chat_example::@056c4f61b0156d1d9b06",
					"jsonFile" : "target-flutter_chat_example-Debug-8a4f206f07e029a9941b.json",
					"name" : "flutter_chat_example",
					"projectIndex" : 1
				},
				{
					"directoryIndex" : 1,
					"id" : "flutter_wrapper_app::@2bb09fbb03a373b2cb34",
					"jsonFile" : "target-flutter_wrapper_app-Debug-a8c62e4a3375d634b611.json",
					"name" : "flutter_wrapper_app",
					"projectIndex" : 0
				},
				{
					"directoryIndex" : 1,
					"id" : "flutter_wrapper_plugin::@2bb09fbb03a373b2cb34",
					"jsonFile" : "target-flutter_wrapper_plugin-Debug-6fc437865ddfbe79ac11.json",
					"name" : "flutter_wrapper_plugin",
					"projectIndex" : 0
				}
			]
		}
	],
	"kind" : "codemodel",
	"paths" : 
	{
		"build" : "C:/Users/tnfy1/Documents/flutter_chat_example/windows/out/build/x64-Debug",
		"source" : "C:/Users/tnfy1/Documents/flutter_chat_example/windows"
	},
	"version" : 
	{
		"major" : 2,
		"minor" : 3
	}
}
